handgpt/__init__.py
handgpt/config.py
handgpt/handgpt.py
handgpt-0.1.2.dist-info/LICENSE
handgpt-0.1.2.dist-info/METADATA
handgpt-0.1.2.dist-info/WHEEL
handgpt-0.1.2.dist-info/top_level.txt
handgpt-0.1.2.dist-info/RECORD
