Metadata-Version: 2.1
Name: handgpt
Version: 0.1.2
Summary: A simple tool for HandGPT
Home-page: https://github.com/handgpt/HandGPT
Author: Xener
Author-email: github@handgpt.app
License: MIT
Platform: UNKNOWN
Classifier: Programming Language :: Python :: 3
Classifier: License :: OSI Approved :: MIT License
Classifier: Operating System :: OS Independent
Requires-Python: >=3.9
License-File: LICENSE
Requires-Dist: websockets (>=14.1)
